README
setup.py
lib/cli/__init__.py
lib/cli/compat.py
lib/cli/context.py
lib/cli/error.py
lib/cli/main.py
lib/cli/object.py
lib/cli/parser.py
lib/cli/plyparse.py
lib/cli/settings.py
lib/cli/terminal.py
lib/cli/command/__init__.py
lib/cli/command/cd.py
lib/cli/command/clear.py
lib/cli/command/command.py
lib/cli/command/exit.py
lib/cli/command/help.py
lib/cli/command/pwd.py
lib/cli/command/save.py
lib/cli/command/set.py
lib/cli/command/status.py
lib/cli/platform/__init__.py
lib/cli/platform/posix/__init__.py
lib/cli/platform/posix/terminal.py
lib/cli/platform/posix/util.py
lib/python_cli.egg-info/PKG-INFO
lib/python_cli.egg-info/SOURCES.txt
lib/python_cli.egg-info/dependency_links.txt
lib/python_cli.egg-info/entry_points.txt
lib/python_cli.egg-info/requires.txt
lib/python_cli.egg-info/top_level.txt