Metadata-Version: 1.0
Name: python-cli
Version: 1.2
Summary: A toolkit for CLI construction
Home-page: http://bitbucket.org/geertj/python-cli
Author: Geert Jansen
Author-email: gjansen@redhat.com
License: MIT
Platform: UNKNOWN
Classifier: Development Status :: 4 - Beta
Classifier: Environment :: Console
Classifier: Intended Audience :: Developers
Classifier: License :: OSI Approved :: MIT License
Classifier: Operating System :: OS Independent
Classifier: Programming Language :: Python :: 2.4
Classifier: Programming Language :: Python :: 3
